ztlearn/__init__.py
ztlearn/__version__.py
ztlearn/activations.py
ztlearn/decayers.py
ztlearn/initializers.py
ztlearn/objectives.py
ztlearn/optimizers.py
ztlearn/regularizers.py
ztlearn/datasets/__init__.py
ztlearn/datasets/data_set.py
ztlearn/datasets/boston/__init__.py
ztlearn/datasets/boston/boston_housing.py
ztlearn/datasets/cifar/__init__.py
ztlearn/datasets/cifar/cifar_10/__init__.py
ztlearn/datasets/cifar/cifar_10/cifar_10.py
ztlearn/datasets/cifar/cifar_100/__init__.py
ztlearn/datasets/cifar/cifar_100/cifar_100.py
ztlearn/datasets/digits/__init__.py
ztlearn/datasets/digits/digits.py
ztlearn/datasets/fashion/__init__.py
ztlearn/datasets/fashion/fashion_mnist.py
ztlearn/datasets/iris/__init__.py
ztlearn/datasets/iris/iris.py
ztlearn/datasets/mnist/__init__.py
ztlearn/datasets/mnist/mnist.py
ztlearn/datasets/pima/__init__.py
ztlearn/datasets/pima/pima_indians.py
ztlearn/dl/__init__.py
ztlearn/dl/layers/__init__.py
ztlearn/dl/layers/base.py
ztlearn/dl/layers/convolutional.py
ztlearn/dl/layers/core.py
ztlearn/dl/layers/embedding.py
ztlearn/dl/layers/normalization.py
ztlearn/dl/layers/pooling.py
ztlearn/dl/layers/recurrent/__init__.py
ztlearn/dl/layers/recurrent/gru.py
ztlearn/dl/layers/recurrent/lstm.py
ztlearn/dl/layers/recurrent/rnn.py
ztlearn/dl/models/__init__.py
ztlearn/dl/models/sequential.py
ztlearn/dl/models/trainer.py
ztlearn/maxent/__init__.py
ztlearn/maxent/base.py
ztlearn/maxent/mindivmodel.py
ztlearn/ml/__init__.py
ztlearn/ml/classification/__init__.py
ztlearn/ml/classification/knn.py
ztlearn/ml/classification/perceptron.py
ztlearn/ml/clustering/__init__.py
ztlearn/ml/clustering/kmeans.py
ztlearn/ml/decomposition/__init__.py
ztlearn/ml/decomposition/pca.py
ztlearn/ml/regression/__init__.py
ztlearn/ml/regression/base.py
ztlearn/ml/regression/elasticnet.py
ztlearn/ml/regression/linear.py
ztlearn/ml/regression/logistic.py
ztlearn/ml/regression/polynomial.py
ztlearn/toolkit/__init__.py
ztlearn/toolkit/optviz.py
ztlearn/utils/__init__.py
ztlearn-1.1.5.dist-info/LICENSE
ztlearn-1.1.5.dist-info/METADATA
ztlearn-1.1.5.dist-info/WHEEL
ztlearn-1.1.5.dist-info/top_level.txt
ztlearn-1.1.5.dist-info/RECORD
