Metadata-Version: 2.1
Name: ztlearn
Version: 1.1.5
Summary: Minimalistic Python Machine Learning Toolkit.
Home-page: https://github.com/jefkine/zeta-learn
Author: Jefkine Kafunah
Author-email: jefkine@gmail.com
License: MIT
Platform: UNKNOWN
Classifier: Development Status :: 4 - Beta
Classifier: Intended Audience :: Developers
Classifier: Intended Audience :: Education
Classifier: Intended Audience :: Science/Research
Classifier: License :: OSI Approved :: MIT License
Classifier: Programming Language :: Python :: 3
Classifier: Programming Language :: Python :: 3.6
Classifier: Topic :: Software Development :: Libraries
Classifier: Topic :: Software Development :: Libraries :: Python Modules
Classifier: Topic :: Scientific/Engineering :: Artificial Intelligence
Requires-Python: >=3.5.0
Requires-Dist: numpy
Requires-Dist: matplotlib
Requires-Dist: scipy
